{
	"darkmode": true,
	"themeLocation": "theme.json",
	"pages": [
		{
			"path": "pages/place-an-order/index",
			"style": {
				"navigationBarTitleText": "核对订单"
			}
		},
		{
			"path": "pages/index/index",
			"style": {
				"navigationBarTitleText": "首页"
			}
		},
		{
			"path": "pages/payment/index",
			"style": {
				"navigationBarTitleText": "已下单"
			}
		},
		{
			"path": "pages/invite/index",
			"style": {
				"navigationBarTitleText": "我的邀请码"
			}
		},
		{
			"path": "pages/lnvitation-code/index",
			"style": {
				"navigationBarTitleText": "输入邀请码"
			}
		},
		{
			"path": "pages/qualifications/index",
			"style": {
				"navigationBarTitleText": "资质审核"
			}
		},
		{
			"path": "pages/address/index",
			"style": {
				"navigationBarTitleText": "新增地址"
			}
		},
		{
			"path": "pages/login/index",
			"style": {
				"navigationBarTitleText": "登录"
			}
		},
		{
			"path": "pages/salesman/order/index",
			"style": {
				"navigationBarTitleText": "订单"
			}
		},
	
		{
			"path": "pages/contact/index",
			"style": {
				"navigationBarTitleText": "联系客服"
			}
		}
	],
	"globalStyle": {
		"navigationStyle": "custom",
		"navigationBarTitleText": "采多多",
		"navigationBarBackgroundColor": "@navBarBgColor",
		"navigationBarTextStyle": "@navBarTxtStyle",
		"backgroundColor": "@bgColor",
		"backgroundTextStyle": "@bgTextStyle"
	}
}
